[
  {
    "Jahr": 2024,
    "Monat": "Jaenner",
    "Grundpreis in EUR/Jahr Netto Wien": "",
    "Grundpreis in EUR/Jahr Netto NOE": "",
    "Grundpreis in EUR/Jahr Brutto Wien": "",
    "Grundpreis in EUR/Jahr Brutto NOE": "",
    "Verbrauchspreis in Cent/kWh Netto Wien": "16,5766",
    "Verbrauchspreis in Cent/kWh Netto NOE": "16,5766",
    "Verbrauchspreis in Cent/kWh Brutto Wien": "",
    "Verbrauchspreis in Cent/kWh Brutto NOE": "",
    "Grundpreis Aktion NOE": "",
    "Grundpreis Aktion Wien": "",
    "Verbrauchspreis Aktion NOE": "",
    "Verbrauchspreis Aktion Wien": ""
  },
  {
    "Jahr": 2024,
    "Monat": "Februar",
    "Grundpreis in EUR/Jahr Netto Wien": "",
    "Grundpreis in EUR/Jahr Netto NOE": "",
    "Grundpreis in EUR/Jahr Brutto Wien": "",
    "Grundpreis in EUR/Jahr Brutto NOE": "",
    "Verbrauchspreis in Cent/kWh Netto Wien": "16,5766",
    "Verbrauchspreis in Cent/kWh Netto NOE": "16,5766",
    "Verbrauchspreis in Cent/kWh Brutto Wien": "",
    "Verbrauchspreis in Cent/kWh Brutto NOE": "",
    "Grundpreis Aktion NOE": "",
    "Grundpreis Aktion Wien": "",
    "Verbrauchspreis Aktion NOE": "",
    "Verbrauchspreis Aktion Wien": ""
  },
  {
    "Jahr": 2024,
    "Monat": "Maerz",
    "Grundpreis in EUR/Jahr Netto Wien": "",
    "Grundpreis in EUR/Jahr Netto NOE": "",
    "Grundpreis in EUR/Jahr Brutto Wien": "",
    "Grundpreis in EUR/Jahr Brutto NOE": "",
    "Verbrauchspreis in Cent/kWh Netto Wien": "16,5766",
    "Verbrauchspreis in Cent/kWh Netto NOE": "16,5766",
    "Verbrauchspreis in Cent/kWh Brutto Wien": "",
    "Verbrauchspreis in Cent/kWh Brutto NOE": "",
    "Grundpreis Aktion NOE": "",
    "Grundpreis Aktion Wien": "",
    "Verbrauchspreis Aktion NOE": "",
    "Verbrauchspreis Aktion Wien": ""
  },
  {
    "Jahr": 2024,
    "Monat": "April",
    "Grundpreis in EUR/Jahr Netto Wien": "",
    "Grundpreis in EUR/Jahr Netto NOE": "",
    "Grundpreis in EUR/Jahr Brutto Wien": "",
    "Grundpreis in EUR/Jahr Brutto NOE": "",
    "Verbrauchspreis in Cent/kWh Netto Wien": "12,0448",
    "Verbrauchspreis in Cent/kWh Netto NOE": "12,0448",
    "Verbrauchspreis in Cent/kWh Brutto Wien": "",
    "Verbrauchspreis in Cent/kWh Brutto NOE": "",
    "Grundpreis Aktion NOE": "",
    "Grundpreis Aktion Wien": "",
    "Verbrauchspreis Aktion NOE": "",
    "Verbrauchspreis Aktion Wien": ""
  },
  {
    "Jahr": 2024,
    "Monat": "Mai",
    "Grundpreis in EUR/Jahr Netto Wien": "",
    "Grundpreis in EUR/Jahr Netto NOE": "",
    "Grundpreis in EUR/Jahr Brutto Wien": "",
    "Grundpreis in EUR/Jahr Brutto NOE": "",
    "Verbrauchspreis in Cent/kWh Netto Wien": "12,0448",
    "Verbrauchspreis in Cent/kWh Netto NOE": "12,0448",
    "Verbrauchspreis in Cent/kWh Brutto Wien": "",
    "Verbrauchspreis in Cent/kWh Brutto NOE": "",
    "Grundpreis Aktion NOE": "",
    "Grundpreis Aktion Wien": "",
    "Verbrauchspreis Aktion NOE": "",
    "Verbrauchspreis Aktion Wien": ""
  },
  {
    "Jahr": 2024,
    "Monat": "Juni",
    "Grundpreis in EUR/Jahr Netto Wien": "",
    "Grundpreis in EUR/Jahr Netto NOE": "",
    "Grundpreis in EUR/Jahr Brutto Wien": "",
    "Grundpreis in EUR/Jahr Brutto NOE": "",
    "Verbrauchspreis in Cent/kWh Netto Wien": "12,0448",
    "Verbrauchspreis in Cent/kWh Netto NOE": "12,0448",
    "Verbrauchspreis in Cent/kWh Brutto Wien": "",
    "Verbrauchspreis in Cent/kWh Brutto NOE": "",
    "Grundpreis Aktion NOE": "",
    "Grundpreis Aktion Wien": "",
    "Verbrauchspreis Aktion NOE": "",
    "Verbrauchspreis Aktion Wien": ""
  },
  {
    "Jahr": 2024,
    "Monat": "Juli",
    "Grundpreis in EUR/Jahr Netto Wien": "",
    "Grundpreis in EUR/Jahr Netto NOE": "",
    "Grundpreis in EUR/Jahr Brutto Wien": "",
    "Grundpreis in EUR/Jahr Brutto NOE": "",
    "Verbrauchspreis in Cent/kWh Netto Wien": "12,0448",
    "Verbrauchspreis in Cent/kWh Netto NOE": "12,0448",
    "Verbrauchspreis in Cent/kWh Brutto Wien": "",
    "Verbrauchspreis in Cent/kWh Brutto NOE": "",
    "Grundpreis Aktion NOE": "",
    "Grundpreis Aktion Wien": "",
    "Verbrauchspreis Aktion NOE": "",
    "Verbrauchspreis Aktion Wien": ""
  },
  {
    "Jahr": 2024,
    "Monat": "August",
    "Grundpreis in EUR/Jahr Netto Wien": "",
    "Grundpreis in EUR/Jahr Netto NOE": "",
    "Grundpreis in EUR/Jahr Brutto Wien": "",
    "Grundpreis in EUR/Jahr Brutto NOE": "",
    "Verbrauchspreis in Cent/kWh Netto Wien": "12,0448",
    "Verbrauchspreis in Cent/kWh Netto NOE": "12,0448",
    "Verbrauchspreis in Cent/kWh Brutto Wien": "",
    "Verbrauchspreis in Cent/kWh Brutto NOE": "",
    "Grundpreis Aktion NOE": "",
    "Grundpreis Aktion Wien": "",
    "Verbrauchspreis Aktion NOE": "",
    "Verbrauchspreis Aktion Wien": ""
  },
  {
    "Jahr": 2024,
    "Monat": "September",
    "Grundpreis in EUR/Jahr Netto Wien": "",
    "Grundpreis in EUR/Jahr Netto NOE": "",
    "Grundpreis in EUR/Jahr Brutto Wien": "",
    "Grundpreis in EUR/Jahr Brutto NOE": "",
    "Verbrauchspreis in Cent/kWh Netto Wien": "12,0448",
    "Verbrauchspreis in Cent/kWh Netto NOE": "12,0448",
    "Verbrauchspreis in Cent/kWh Brutto Wien": "",
    "Verbrauchspreis in Cent/kWh Brutto NOE": "",
    "Grundpreis Aktion NOE": "",
    "Grundpreis Aktion Wien": "",
    "Verbrauchspreis Aktion NOE": "",
    "Verbrauchspreis Aktion Wien": ""
  },
  {
    "Jahr": 2024,
    "Monat": "Oktober",
    "Grundpreis in EUR/Jahr Netto Wien": "",
    "Grundpreis in EUR/Jahr Netto NOE": "",
    "Grundpreis in EUR/Jahr Brutto Wien": "",
    "Grundpreis in EUR/Jahr Brutto NOE": "",
    "Verbrauchspreis in Cent/kWh Netto Wien": "9,0151",
    "Verbrauchspreis in Cent/kWh Netto NOE": "9,0151",
    "Verbrauchspreis in Cent/kWh Brutto Wien": "",
    "Verbrauchspreis in Cent/kWh Brutto NOE": "",
    "Grundpreis Aktion NOE": "",
    "Grundpreis Aktion Wien": "",
    "Verbrauchspreis Aktion NOE": "",
    "Verbrauchspreis Aktion Wien": ""
  },
  {
    "Jahr": 2024,
    "Monat": "November",
    "Grundpreis in EUR/Jahr Netto Wien": "",
    "Grundpreis in EUR/Jahr Netto NOE": "",
    "Grundpreis in EUR/Jahr Brutto Wien": "",
    "Grundpreis in EUR/Jahr Brutto NOE": "",
    "Verbrauchspreis in Cent/kWh Netto Wien": "9,0151",
    "Verbrauchspreis in Cent/kWh Netto NOE": "9,0151",
    "Verbrauchspreis in Cent/kWh Brutto Wien": "",
    "Verbrauchspreis in Cent/kWh Brutto NOE": "",
    "Grundpreis Aktion NOE": "",
    "Grundpreis Aktion Wien": "",
    "Verbrauchspreis Aktion NOE": "",
    "Verbrauchspreis Aktion Wien": ""
  },
  {
    "Jahr": 2024,
    "Monat": "Dezember",
    "Grundpreis in EUR/Jahr Netto Wien": "",
    "Grundpreis in EUR/Jahr Netto NOE": "",
    "Grundpreis in EUR/Jahr Brutto Wien": "",
    "Grundpreis in EUR/Jahr Brutto NOE": "",
    "Verbrauchspreis in Cent/kWh Netto Wien": "9,0151",
    "Verbrauchspreis in Cent/kWh Netto NOE": "9,0151",
    "Verbrauchspreis in Cent/kWh Brutto Wien": "",
    "Verbrauchspreis in Cent/kWh Brutto NOE": "",
    "Grundpreis Aktion NOE": "",
    "Grundpreis Aktion Wien": "",
    "Verbrauchspreis Aktion NOE": "",
    "Verbrauchspreis Aktion Wien": ""
  },
  {
    "Jahr": 2025,
    "Monat": "Jaenner",
    "Grundpreis in EUR/Jahr Netto Wien": "",
    "Grundpreis in EUR/Jahr Netto NOE": "",
    "Grundpreis in EUR/Jahr Brutto Wien": "",
    "Grundpreis in EUR/Jahr Brutto NOE": "",
    "Verbrauchspreis in Cent/kWh Netto Wien": "9,0151",
    "Verbrauchspreis in Cent/kWh Netto NOE": "9,0151",
    "Verbrauchspreis in Cent/kWh Brutto Wien": "",
    "Verbrauchspreis in Cent/kWh Brutto NOE": "",
    "Grundpreis Aktion NOE": "",
    "Grundpreis Aktion Wien": "",
    "Verbrauchspreis Aktion NOE": "",
    "Verbrauchspreis Aktion Wien": ""
  },
  {
    "Jahr": 2025,
    "Monat": "Februar",
    "Grundpreis in EUR/Jahr Netto Wien": "",
    "Grundpreis in EUR/Jahr Netto NOE": "",
    "Grundpreis in EUR/Jahr Brutto Wien": "",
    "Grundpreis in EUR/Jahr Brutto NOE": "",
    "Verbrauchspreis in Cent/kWh Netto Wien": "9,0151",
    "Verbrauchspreis in Cent/kWh Netto NOE": "9,0151",
    "Verbrauchspreis in Cent/kWh Brutto Wien": "",
    "Verbrauchspreis in Cent/kWh Brutto NOE": "",
    "Grundpreis Aktion NOE": "",
    "Grundpreis Aktion Wien": "",
    "Verbrauchspreis Aktion NOE": "",
    "Verbrauchspreis Aktion Wien": ""
  },
  {
    "Jahr": 2025,
    "Monat": "Maerz",
    "Grundpreis in EUR/Jahr Netto Wien": "",
    "Grundpreis in EUR/Jahr Netto NOE": "",
    "Grundpreis in EUR/Jahr Brutto Wien": "",
    "Grundpreis in EUR/Jahr Brutto NOE": "",
    "Verbrauchspreis in Cent/kWh Netto Wien": "9,0151",
    "Verbrauchspreis in Cent/kWh Netto NOE": "9,0151",
    "Verbrauchspreis in Cent/kWh Brutto Wien": "",
    "Verbrauchspreis in Cent/kWh Brutto NOE": "",
    "Grundpreis Aktion NOE": "",
    "Grundpreis Aktion Wien": "",
    "Verbrauchspreis Aktion NOE": "",
    "Verbrauchspreis Aktion Wien": ""
  },
  {
    "Jahr": 2025,
    "Monat": "April",
    "Grundpreis in EUR/Jahr Netto Wien": "",
    "Grundpreis in EUR/Jahr Netto NOE": "",
    "Grundpreis in EUR/Jahr Brutto Wien": "",
    "Grundpreis in EUR/Jahr Brutto NOE": "",
    "Verbrauchspreis in Cent/kWh Netto Wien": "9,0151",
    "Verbrauchspreis in Cent/kWh Netto NOE": "9,0151",
    "Verbrauchspreis in Cent/kWh Brutto Wien": "",
    "Verbrauchspreis in Cent/kWh Brutto NOE": "",
    "Grundpreis Aktion NOE": "",
    "Grundpreis Aktion Wien": "",
    "Verbrauchspreis Aktion NOE": "",
    "Verbrauchspreis Aktion Wien": ""
  },
  {
    "Jahr": 2025,
    "Monat": "Mai",
    "Grundpreis in EUR/Jahr Netto Wien": "",
    "Grundpreis in EUR/Jahr Netto NOE": "",
    "Grundpreis in EUR/Jahr Brutto Wien": "",
    "Grundpreis in EUR/Jahr Brutto NOE": "",
    "Verbrauchspreis in Cent/kWh Netto Wien": "9,1328",
    "Verbrauchspreis in Cent/kWh Netto NOE": "9,1328",
    "Verbrauchspreis in Cent/kWh Brutto Wien": "",
    "Verbrauchspreis in Cent/kWh Brutto NOE": "",
    "Grundpreis Aktion NOE": "",
    "Grundpreis Aktion Wien": "",
    "Verbrauchspreis Aktion NOE": "",
    "Verbrauchspreis Aktion Wien": ""
  },
  {
    "Jahr": 2025,
    "Monat": "Juni",
    "Grundpreis in EUR/Jahr Netto Wien": "",
    "Grundpreis in EUR/Jahr Netto NOE": "",
    "Grundpreis in EUR/Jahr Brutto Wien": "",
    "Grundpreis in EUR/Jahr Brutto NOE": "",
    "Verbrauchspreis in Cent/kWh Netto Wien": "9,1328",
    "Verbrauchspreis in Cent/kWh Netto NOE": "9,1328",
    "Verbrauchspreis in Cent/kWh Brutto Wien": "",
    "Verbrauchspreis in Cent/kWh Brutto NOE": "",
    "Grundpreis Aktion NOE": "",
    "Grundpreis Aktion Wien": "",
    "Verbrauchspreis Aktion NOE": "",
    "Verbrauchspreis Aktion Wien": ""
  },
  {
    "Jahr": 2025,
    "Monat": "Juli",
    "Grundpreis in EUR/Jahr Netto Wien": "",
    "Grundpreis in EUR/Jahr Netto NOE": "",
    "Grundpreis in EUR/Jahr Brutto Wien": "",
    "Grundpreis in EUR/Jahr Brutto NOE": "",
    "Verbrauchspreis in Cent/kWh Netto Wien": "9,1328",
    "Verbrauchspreis in Cent/kWh Netto NOE": "9,1328",
    "Verbrauchspreis in Cent/kWh Brutto Wien": "",
    "Verbrauchspreis in Cent/kWh Brutto NOE": "",
    "Grundpreis Aktion NOE": "",
    "Grundpreis Aktion Wien": "",
    "Verbrauchspreis Aktion NOE": "",
    "Verbrauchspreis Aktion Wien": ""
  },
  {
    "Jahr": 2025,
    "Monat": "August",
    "Grundpreis in EUR/Jahr Netto Wien": "",
    "Grundpreis in EUR/Jahr Netto NOE": "",
    "Grundpreis in EUR/Jahr Brutto Wien": "",
    "Grundpreis in EUR/Jahr Brutto NOE": "",
    "Verbrauchspreis in Cent/kWh Netto Wien": "9,1328",
    "Verbrauchspreis in Cent/kWh Netto NOE": "9,1328",
    "Verbrauchspreis in Cent/kWh Brutto Wien": "",
    "Verbrauchspreis in Cent/kWh Brutto NOE": "",
    "Grundpreis Aktion NOE": "",
    "Grundpreis Aktion Wien": "",
    "Verbrauchspreis Aktion NOE": "",
    "Verbrauchspreis Aktion Wien": ""
  },
  {
    "Jahr": 2025,
    "Monat": "September",
    "Grundpreis in EUR/Jahr Netto Wien": "",
    "Grundpreis in EUR/Jahr Netto NOE": "",
    "Grundpreis in EUR/Jahr Brutto Wien": "",
    "Grundpreis in EUR/Jahr Brutto NOE": "",
    "Verbrauchspreis in Cent/kWh Netto Wien": "9,1328",
    "Verbrauchspreis in Cent/kWh Netto NOE": "9,1328",
    "Verbrauchspreis in Cent/kWh Brutto Wien": "",
    "Verbrauchspreis in Cent/kWh Brutto NOE": "",
    "Grundpreis Aktion NOE": "",
    "Grundpreis Aktion Wien": "",
    "Verbrauchspreis Aktion NOE": "",
    "Verbrauchspreis Aktion Wien": ""
  },
  {
    "Jahr": 2025,
    "Monat": "Oktober",
    "Grundpreis in EUR/Jahr Netto Wien": "",
    "Grundpreis in EUR/Jahr Netto NOE": "",
    "Grundpreis in EUR/Jahr Brutto Wien": "",
    "Grundpreis in EUR/Jahr Brutto NOE": "",
    "Verbrauchspreis in Cent/kWh Netto Wien": "9,0579",
    "Verbrauchspreis in Cent/kWh Netto NOE": "9,0579",
    "Verbrauchspreis in Cent/kWh Brutto Wien": "",
    "Verbrauchspreis in Cent/kWh Brutto NOE": "",
    "Grundpreis Aktion NOE": "",
    "Grundpreis Aktion Wien": "",
    "Verbrauchspreis Aktion NOE": "",
    "Verbrauchspreis Aktion Wien": ""
  },
  {
    "Jahr": 2025,
    "Monat": "November",
    "Grundpreis in EUR/Jahr Netto Wien": "",
    "Grundpreis in EUR/Jahr Netto NOE": "",
    "Grundpreis in EUR/Jahr Brutto Wien": "",
    "Grundpreis in EUR/Jahr Brutto NOE": "",
    "Verbrauchspreis in Cent/kWh Netto Wien": "9,0579",
    "Verbrauchspreis in Cent/kWh Netto NOE": "9,0579",
    "Verbrauchspreis in Cent/kWh Brutto Wien": "",
    "Verbrauchspreis in Cent/kWh Brutto NOE": "",
    "Grundpreis Aktion NOE": "",
    "Grundpreis Aktion Wien": "",
    "Verbrauchspreis Aktion NOE": "",
    "Verbrauchspreis Aktion Wien": ""
  },
  {
    "Jahr": 2025,
    "Monat": "Dezember",
    "Grundpreis in EUR/Jahr Netto Wien": "",
    "Grundpreis in EUR/Jahr Netto NOE": "",
    "Grundpreis in EUR/Jahr Brutto Wien": "",
    "Grundpreis in EUR/Jahr Brutto NOE": "",
    "Verbrauchspreis in Cent/kWh Netto Wien": "9,0579",
    "Verbrauchspreis in Cent/kWh Netto NOE": "9,0579",
    "Verbrauchspreis in Cent/kWh Brutto Wien": "",
    "Verbrauchspreis in Cent/kWh Brutto NOE": "",
    "Grundpreis Aktion NOE": "",
    "Grundpreis Aktion Wien": "",
    "Verbrauchspreis Aktion NOE": "",
    "Verbrauchspreis Aktion Wien": ""
  },
  {
    "Jahr": 2026,
    "Monat": "Jaenner",
    "Grundpreis in EUR/Jahr Netto Wien": "",
    "Grundpreis in EUR/Jahr Netto NOE": "",
    "Grundpreis in EUR/Jahr Brutto Wien": "",
    "Grundpreis in EUR/Jahr Brutto NOE": "",
    "Verbrauchspreis in Cent/kWh Netto Wien": "9,0579",
    "Verbrauchspreis in Cent/kWh Netto NOE": "9,0579",
    "Verbrauchspreis in Cent/kWh Brutto Wien": "",
    "Verbrauchspreis in Cent/kWh Brutto NOE": "",
    "Grundpreis Aktion NOE": "",
    "Grundpreis Aktion Wien": "",
    "Verbrauchspreis Aktion NOE": "",
    "Verbrauchspreis Aktion Wien": ""
  },
  {
    "Jahr": 2026,
    "Monat": "Februar",
    "Grundpreis in EUR/Jahr Netto Wien": "",
    "Grundpreis in EUR/Jahr Netto NOE": "",
    "Grundpreis in EUR/Jahr Brutto Wien": "",
    "Grundpreis in EUR/Jahr Brutto NOE": "",
    "Verbrauchspreis in Cent/kWh Netto Wien": "9,0579",
    "Verbrauchspreis in Cent/kWh Netto NOE": "9,0579",
    "Verbrauchspreis in Cent/kWh Brutto Wien": "",
    "Verbrauchspreis in Cent/kWh Brutto NOE": "",
    "Grundpreis Aktion NOE": "",
    "Grundpreis Aktion Wien": "",
    "Verbrauchspreis Aktion NOE": "",
    "Verbrauchspreis Aktion Wien": ""
  },
  {
    "Jahr": 2026,
    "Monat": "Maerz",
    "Grundpreis in EUR/Jahr Netto Wien": "",
    "Grundpreis in EUR/Jahr Netto NOE": "",
    "Grundpreis in EUR/Jahr Brutto Wien": "",
    "Grundpreis in EUR/Jahr Brutto NOE": "",
    "Verbrauchspreis in Cent/kWh Netto Wien": "9,0579",
    "Verbrauchspreis in Cent/kWh Netto NOE": "9,0579",
    "Verbrauchspreis in Cent/kWh Brutto Wien": "",
    "Verbrauchspreis in Cent/kWh Brutto NOE": "",
    "Grundpreis Aktion NOE": "",
    "Grundpreis Aktion Wien": "",
    "Verbrauchspreis Aktion NOE": "",
    "Verbrauchspreis Aktion Wien": ""
  },
  {
    "Jahr": 2026,
    "Monat": "April",
    "Grundpreis in EUR/Jahr Netto Wien": "",
    "Grundpreis in EUR/Jahr Netto NOE": "",
    "Grundpreis in EUR/Jahr Brutto Wien": "",
    "Grundpreis in EUR/Jahr Brutto NOE": "",
    "Verbrauchspreis in Cent/kWh Netto Wien": "",
    "Verbrauchspreis in Cent/kWh Netto NOE": "",
    "Verbrauchspreis in Cent/kWh Brutto Wien": "",
    "Verbrauchspreis in Cent/kWh Brutto NOE": "",
    "Grundpreis Aktion NOE": "",
    "Grundpreis Aktion Wien": "",
    "Verbrauchspreis Aktion NOE": "",
    "Verbrauchspreis Aktion Wien": ""
  },
  {
    "Jahr": 2026,
    "Monat": "Mai",
    "Grundpreis in EUR/Jahr Netto Wien": "",
    "Grundpreis in EUR/Jahr Netto NOE": "",
    "Grundpreis in EUR/Jahr Brutto Wien": "",
    "Grundpreis in EUR/Jahr Brutto NOE": "",
    "Verbrauchspreis in Cent/kWh Netto Wien": "",
    "Verbrauchspreis in Cent/kWh Netto NOE": "",
    "Verbrauchspreis in Cent/kWh Brutto Wien": "",
    "Verbrauchspreis in Cent/kWh Brutto NOE": "",
    "Grundpreis Aktion NOE": "",
    "Grundpreis Aktion Wien": "",
    "Verbrauchspreis Aktion NOE": "",
    "Verbrauchspreis Aktion Wien": ""
  },
  {
    "Jahr": 2026,
    "Monat": "Juni",
    "Grundpreis in EUR/Jahr Netto Wien": "",
    "Grundpreis in EUR/Jahr Netto NOE": "",
    "Grundpreis in EUR/Jahr Brutto Wien": "",
    "Grundpreis in EUR/Jahr Brutto NOE": "",
    "Verbrauchspreis in Cent/kWh Netto Wien": "",
    "Verbrauchspreis in Cent/kWh Netto NOE": "",
    "Verbrauchspreis in Cent/kWh Brutto Wien": "",
    "Verbrauchspreis in Cent/kWh Brutto NOE": "",
    "Grundpreis Aktion NOE": "",
    "Grundpreis Aktion Wien": "",
    "Verbrauchspreis Aktion NOE": "",
    "Verbrauchspreis Aktion Wien": ""
  },
  {
    "Jahr": 2026,
    "Monat": "Juli",
    "Grundpreis in EUR/Jahr Netto Wien": "",
    "Grundpreis in EUR/Jahr Netto NOE": "",
    "Grundpreis in EUR/Jahr Brutto Wien": "",
    "Grundpreis in EUR/Jahr Brutto NOE": "",
    "Verbrauchspreis in Cent/kWh Netto Wien": "",
    "Verbrauchspreis in Cent/kWh Netto NOE": "",
    "Verbrauchspreis in Cent/kWh Brutto Wien": "",
    "Verbrauchspreis in Cent/kWh Brutto NOE": "",
    "Grundpreis Aktion NOE": "",
    "Grundpreis Aktion Wien": "",
    "Verbrauchspreis Aktion NOE": "",
    "Verbrauchspreis Aktion Wien": ""
  },
  {
    "Jahr": 2026,
    "Monat": "August",
    "Grundpreis in EUR/Jahr Netto Wien": "",
    "Grundpreis in EUR/Jahr Netto NOE": "",
    "Grundpreis in EUR/Jahr Brutto Wien": "",
    "Grundpreis in EUR/Jahr Brutto NOE": "",
    "Verbrauchspreis in Cent/kWh Netto Wien": "",
    "Verbrauchspreis in Cent/kWh Netto NOE": "",
    "Verbrauchspreis in Cent/kWh Brutto Wien": "",
    "Verbrauchspreis in Cent/kWh Brutto NOE": "",
    "Grundpreis Aktion NOE": "",
    "Grundpreis Aktion Wien": "",
    "Verbrauchspreis Aktion NOE": "",
    "Verbrauchspreis Aktion Wien": ""
  },
  {
    "Jahr": 2026,
    "Monat": "September",
    "Grundpreis in EUR/Jahr Netto Wien": "",
    "Grundpreis in EUR/Jahr Netto NOE": "",
    "Grundpreis in EUR/Jahr Brutto Wien": "",
    "Grundpreis in EUR/Jahr Brutto NOE": "",
    "Verbrauchspreis in Cent/kWh Netto Wien": "",
    "Verbrauchspreis in Cent/kWh Netto NOE": "",
    "Verbrauchspreis in Cent/kWh Brutto Wien": "",
    "Verbrauchspreis in Cent/kWh Brutto NOE": "",
    "Grundpreis Aktion NOE": "",
    "Grundpreis Aktion Wien": "",
    "Verbrauchspreis Aktion NOE": "",
    "Verbrauchspreis Aktion Wien": ""
  },
  {
    "Jahr": 2026,
    "Monat": "Oktober",
    "Grundpreis in EUR/Jahr Netto Wien": "",
    "Grundpreis in EUR/Jahr Netto NOE": "",
    "Grundpreis in EUR/Jahr Brutto Wien": "",
    "Grundpreis in EUR/Jahr Brutto NOE": "",
    "Verbrauchspreis in Cent/kWh Netto Wien": "",
    "Verbrauchspreis in Cent/kWh Netto NOE": "",
    "Verbrauchspreis in Cent/kWh Brutto Wien": "",
    "Verbrauchspreis in Cent/kWh Brutto NOE": "",
    "Grundpreis Aktion NOE": "",
    "Grundpreis Aktion Wien": "",
    "Verbrauchspreis Aktion NOE": "",
    "Verbrauchspreis Aktion Wien": ""
  },
  {
    "Jahr": 2026,
    "Monat": "November",
    "Grundpreis in EUR/Jahr Netto Wien": "",
    "Grundpreis in EUR/Jahr Netto NOE": "",
    "Grundpreis in EUR/Jahr Brutto Wien": "",
    "Grundpreis in EUR/Jahr Brutto NOE": "",
    "Verbrauchspreis in Cent/kWh Netto Wien": "",
    "Verbrauchspreis in Cent/kWh Netto NOE": "",
    "Verbrauchspreis in Cent/kWh Brutto Wien": "",
    "Verbrauchspreis in Cent/kWh Brutto NOE": "",
    "Grundpreis Aktion NOE": "",
    "Grundpreis Aktion Wien": "",
    "Verbrauchspreis Aktion NOE": "",
    "Verbrauchspreis Aktion Wien": ""
  },
  {
    "Jahr": 2026,
    "Monat": "Dezember",
    "Grundpreis in EUR/Jahr Netto Wien": "",
    "Grundpreis in EUR/Jahr Netto NOE": "",
    "Grundpreis in EUR/Jahr Brutto Wien": "",
    "Grundpreis in EUR/Jahr Brutto NOE": "",
    "Verbrauchspreis in Cent/kWh Netto Wien": "",
    "Verbrauchspreis in Cent/kWh Netto NOE": "",
    "Verbrauchspreis in Cent/kWh Brutto Wien": "",
    "Verbrauchspreis in Cent/kWh Brutto NOE": "",
    "Grundpreis Aktion NOE": "",
    "Grundpreis Aktion Wien": "",
    "Verbrauchspreis Aktion NOE": "",
    "Verbrauchspreis Aktion Wien": ""
  }
]